Workbook

Sheet Dashboard
A1: Key Financial Metrics Summary
A2: Metric | B2: 2024 | C2: 2025
A3: Net Profit Margin | B3: ='Key Ratios'!B7 -> 0.26915064 | C3: ='Key Ratios'!C7 -> 0.23971256
A4: Operating Margin | B4: ='Key Ratios'!B8 -> 0.319708 | C4: ='Key Ratios'!C8 -> 0.31510223
A5: Current Ratio | B5: ='Key Ratios'!B11 -> 0.89329292 | C5: ='Key Ratios'!C11 -> 0.86762246
A6: Debt-to-Equity Ratio | B6: ='Key Ratios'!B14 -> 3.8721875 | C6: ='Key Ratios'!C14 -> 5.4087796
A8: Operating Cash flow to net income | B8: ='Key Ratios'!B17 -> 0.99528614 | C8: ='Key Ratios'!C17 -> 1.2615644
A9: free cash flow | B9: ='Key Ratios'!B18 -> 98767 | C9: ='Key Ratios'!C18 -> 109907

Sheet Key Ratios
A1: Apple Inc. | B1: 2025 | C1: 2024
A2: Key Ratios
A3: USD (Millions)
A5: Ratio
A6: Profitability
A7: Net Profit Margin | B7: ='Income Statement'!B26/'Income Statement'!B9 -> 0.26915064 | C7: ='Income Statement'!C26/'Income Statement'!C9 -> 0.23971256
A8: Operating Margin | B8: ='Income Statement'!B21/'Income Statement'!B9 -> 0.319708 | C8: ='Income Statement'!C21/'Income Statement'!C9 -> 0.31510223
A10: Liquidity
A11: Current Ratio | B11: ='Balance Sheet'!B14/'Balance Sheet'!B30 -> 0.89329292 | C11: ='Balance Sheet'!C14/'Balance Sheet'!C30 -> 0.86762246
A13: Leverage
A14: Debt-to-Equity Ratio | B14: ='Balance Sheet'!B37/'Balance Sheet'!B43 -> 3.8721875 | C14: ='Balance Sheet'!C37/'Balance Sheet'!C43 -> 5.4087796
A16: Cash Flow
A17: Operating Cash Flow to Net Income | B17: ='Cash Flow Statement'!B17/'Income Statement'!B26 -> 0.99528614 | C17: ='Cash Flow Statement'!C17/'Income Statement'!C26 -> 1.2615644
A18: Free Cash Flow | B18: ='Cash Flow Statement'!B17+'Cash Flow Statement'!B23 -> 98767 | C18: ='Cash Flow Statement'!C17+'Cash Flow Statement'!C23 -> 109907

Sheet Income Statement
A1: Apple Inc.
A2: Income Statement
A3: USD (Millions)
A5: Item | B5: 2025 | C5: 2024
A6: Net sales
A7: Net sales - Products | B7: 307003 | C7: 294866
A8: Net sales - Services | B8: 109158 | C8: 96169
A9: Total Net Sales | B9: 416161 | C9: 391035
A11: Cost of sales
A12: Cost of sales - Products | B12: 194116 | C12: 185233
A13: Cost of sales - Services | B13: 26844 | C13: 25119
A14: Total Cost of Sales | B14: 220960 | C14: 210352
A15: Gross Margin | B15: 195201 | C15: 180683
A17: Operating expenses
A18: R&D Expense | B18: 34550 | C18: 31370
A19: SG&A Expense | B19: 27601 | C19: 26097
A20: Total Operating Expenses | B20: 62151 | C20: 57467
A21: Operating Income | B21: 133050 | C21: 123216
A23: Other Income (Expense), net | B23: -321 | C23: 269
A24: Income Before Tax | B24: 132729 | C24: 123485
A25: Income Tax Provision | B25: 20719 | C25: 29749
A26: Net Income | B26: 112010 | C26: 93736

Sheet Cash Flow Statement
A1: Apple Inc.
A2: Cash Flow Statement
A3: USD (Millions)
A5: Item | B5: 2025 | C5: 2024
A6: Cash flows from operating activities
A7: Net income | B7: 112010 | C7: 93736
A8: Depreciation and amortization | B8: 11688 | C8: 11445
A9: Share-based compensation expense | B9: 12863 | C9: 11688
A10: Other adjustments | B10: -89 | C10: -2266
A11: Accounts receivable, net | B11: -6682 | C11: -3788
A12: Vendor non-trade receivables | B12: -347 | C12: -1356
A13: Inventories | B13: 1400 | C13: -1046
A14: Other current and non-current assets | B14: -9197 | C14: -11731
A15: Accounts payable | B15: 902 | C15: 6020
A16: Other current and non-current liabilities | B16: -11076 | C16: 15552
A17: Cash generated by operating activities | B17: 111482 | C17: 118254
A19: Cash flows from investing activities
A20: Purchases of marketable securities | B20: -24407 | C20: -48656
A21: Proceeds from maturities of marketable securities | B21: 40907 | C21: 51211
A22: Proceeds from sales of marketable securities | B22: 12890 | C22: 11135
A23: Payments for acquisition of property, plant and equipment | B23: -12715 | C23: -8347
A24: Other investing activities | B24: -1480 | C24: -1308
A25: Cash generated by investing activities | B25: 15195 | C25: 2935
A27: Cash flows from financing activities
A28: Payments for taxes related to net share settlement of equity awards | B28: -5960 | C28: -5441
A29: Payments of dividends and dividend equivalents | B29: -15241 | C29: -15234
A30: Repurchases of common stock | B30: -90711 | C30: -94949
A31: Proceeds from issuance of term debt, net | B31: 4481 | C31: 5228
A32: Repayments of term debt | B32: -10932 | C32: -9858
A33: Proceeds from (repayments of) commercial paper, net | B33: -2032 | C33: 3960
A34: Other financing activities | B34: -111 | C34: -361
A35: Cash used in financing activities | B35: -120566 | C35: -121983
A37: Net change in cash
A38: Increase/(decrease) in cash | B38: 5991 | C38: -794
A39: Beginning cash and cash equivalents | B39: 29943 | C39: 30737
A40: Ending cash and cash equivalents | B40: 35934 | C40: 29943

Sheet Balance Sheet
A1: Apple Inc.
A2: Balance Sheet
A3: USD (Millions)
A6: Item | B6: 2025 | C6: 2024
A7: Current Assets
A8: Cash and cash equivalents | B8: 29943 | C8: 29943
A9: Marketable securities (current) | B9: 18783 | C9: 35228
A10: Accounts receivable, net | B10: 39777 | C10: 33410
A11: Vendor non-trade receivables | B11: 33180 | C11: 32833
A12: Inventories | B12: 5718 | C12: 7286
A13: Other current assets | B13: 14585 | C13: 14287
A14: Total Current Assets | B14: 147957 | C14: 152987
A16: Non-Current Assets
A17: Marketable securities (non-current) | B17: 77723 | C17: 91479
A18: Property, plant and equipment, net | B18: 49834 | C18: 45680
A19: Other non-current assets | B19: 83727 | C19: 74834
A20: Total Non-Current Assets | B20: 211284 | C20: 211993
A22: Total Assets | B22: 359241 | C22: 364980
A24: Current Liabilities
A25: Accounts payable | B25: 69860 | C25: 68960
A26: Other current liabilities | B26: 66387 | C26: 78340
A27: Deferred revenue | B27: 9055 | C27: 8249
A28: Commercial paper | B28: 7979 | C28: 9967
A29: Term debt (current) | B29: 12350 | C29: 10912
A30: Total Current Liabilities | B30: 165631 | C30: 176329
A32: Non-Current Liabilities
A33: Term debt (non-current) | B33: 78328 | C33: 85750
A34: Other non-current liabilities | B34: 41549 | C34: 45888
A35: Total Non-Current Liabilities | B35: 119877 | C35: 131638
A37: Total liabilities | B37: 285508 | C37: 308030
A39: Shareholders' Equity
A40: Common stock and APIC | B40: 93568 | C40: 83276
A41: Accumulated deficit | B41: -14264 | C41: -19154
A42: Accumulated other comprehensive loss | B42: -5571 | C42: -7172
A43: Total shareholders' equity | B43: 73733 | C43: 56950
A45: Total liabilities and shareholders' equity | B45: 359241 | C45: 364980
